[
    {
        "name": "USER MANUAL - 2024 EDITION",
        "size": "200 KB",
        "date": "Event: 24-01-15",
        "type": "document",
        "path": "files/user_manual_2024.pdf",
        "corrupted": false,
        "locked": 2
    },
    {
        "name": "SYSTEM OVERVIEW REPORT",
        "size": "75 KB",
        "date": "2023-11-03",
        "type": "document",
        "path": "files/system_overview_report.docx",
        "corrupted": true
    },
    {
        "name": "SURVEILLANCE FOOTAGE - SECURE AREA 7",
        "size": "500 MB",
        "date": "2024-02-20",
        "type": "video",
        "path": "files/surveillance_footage_area7.mp4",
        "corrupted": false
    },
    {
        "name": "ANOMALY INTERVIEW RECORDING",
        "size": "12 MB",
        "date": "2023-10-12",
        "type": "audio",
        "path": "files/anomaly_interview.mp3",
        "corrupted": false
    },
    {
        "name": "CONFIGURATION FILE - SYSTEM BETA",
        "size": "8 KB",
        "date": "2024-04-01",
        "type": "text",
        "path": "files/config_system_beta.txt",
        "corrupted": false
    },
    {
        "name": "BACKUP DATA - PHASE 3",
        "size": "",
        "date": "2023-09-29",
        "type": "file",
        "path": "files/backup_phase3.zip",
        "corrupted": true
    },
    {
        "name": "DEVELOPER NOTES - VERSION 1.3",
        "size": "45 KB",
        "date": "2024-05-16",
        "type": "document",
        "path": "files/developer_notes_v1_3.pdf",
        "corrupted": false
    },
    {
        "name": "RESEARCH FINDINGS - ANOMALY X",
        "size": "150 KB",
        "date": "2024-03-21",
        "type": "document",
        "path": "files/research_findings_anomaly_x.docx",
        "corrupted": false
    },
    {
        "name": "FIELD TEST RECORDING - DEVICE 7",
        "size": "4 MB",
        "date": "2023-11-09",
        "type": "audio",
        "path": "files/field_test_device7.mp3",
        "corrupted": false
    },
    {
        "name": "TRAINING VIDEO - MODULE 5",
        "size": "120 MB",
        "date": "2024-06-12",
        "type": "video",
        "path": "files/training_video_module5.mp4",
        "corrupted": false
    },
    {
        "name": "RESEARCH DATA - EXPERIMENT ALPHA",
        "size": "300 KB",
        "date": "2024-02-15",
        "type": "document",
        "path": "files/research_data_experiment_alpha.pdf",
        "corrupted": false
    },
    {
        "name": "SYSTEM CONFIGURATION FILE - 2.1",
        "size": "10 KB",
        "date": "2024-03-05",
        "type": "text",
        "path": "files/system_configuration_2_1.txt",
        "corrupted": false
    },
    {
        "name": "SECURITY FOOTAGE - MAIN ENTRANCE",
        "size": "750 MB",
        "date": "2024-07-08",
        "type": "video",
        "path": "files/security_footage_main_entrance.mp4",
        "corrupted": true
    },
    {
        "name": "DEVICE TEST AUDIO - VERSION 3.2",
        "size": "5 MB",
        "date": "2023-12-01",
        "type": "audio",
        "path": "files/device_test_audio_version_3_2.mp3",
        "corrupted": false
    },
    {
        "name": "OPERATIONS MANUAL - SECTOR 9",
        "size": "120 KB",
        "date": "2024-01-28",
        "type": "document",
        "path": "files/operations_manual_sector_9.docx",
        "corrupted": false
    },
    {
        "name": "EXPERIMENT DATA ARCHIVE - SET 4",
        "size": "",
        "date": "2024-05-10",
        "type": "file",
        "path": "files/experiment_data_set_4.zip",
        "corrupted": false
    },
    {
        "name": "TRAINING MODULE - BASIC OPERATIONS",
        "size": "80 MB",
        "date": "2024-08-20",
        "type": "video",
        "path": "files/training_module_basic_operations.mp4",
        "corrupted": false
    },
    {
        "name": "FIELD AUDIO RECORD - SESSION 2",
        "size": "7 MB",
        "date": "2023-11-15",
        "type": "audio",
        "path": "files/field_audio_session_2.mp3",
        "corrupted": false
    },
    {
        "name": "CONFIGURATION NOTES - INTERNAL TEST",
        "size": "25 KB",
        "date": "2024-06-30",
        "type": "text",
        "path": "files/configuration_notes_internal_test.txt",
        "corrupted": true
    },
    {
        "name": "SYSTEM LOG FILE - ERROR REPORT",
        "size": "",
        "date": "2023-10-22",
        "type": "file",
        "path": "files/system_log_error_report.zip",
        "corrupted": false
    }
]
